{
  "landscape": [
    {
      "file": "053dfdae-7275-4ce4-91bc-e88e18562a92.jpg",
      "width": 1086,
      "height": 724,
      "orientation": "landscape",
      "aspectRatio": "1.50"
    },
    {
      "file": "1068a771-9fc7-4d8b-94e4-ee41ce9019db.jpg",
      "width": 1258,
      "height": 625,
      "orientation": "landscape",
      "aspectRatio": "2.01"
    },
    {
      "file": "18635167-96d0-42c2-b9b5-1ec7fea0b840.jpg",
      "width": 1024,
      "height": 768,
      "orientation": "landscape",
      "aspectRatio": "1.33"
    },
    {
      "file": "1dd694e8-8022-4330-b72a-3a9a6713ad52.jpg",
      "width": 1600,
      "height": 823,
      "orientation": "landscape",
      "aspectRatio": "1.94"
    },
    {
      "file": "27f48e3d-522c-405c-8f07-728adb0280d4.jpg",
      "width": 310,
      "height": 163,
      "orientation": "landscape",
      "aspectRatio": "1.90"
    },
    {
      "file": "335e0ceb-8cc4-4e7a-aa8a-fb3238f77359.jpg",
      "width": 1024,
      "height": 768,
      "orientation": "landscape",
      "aspectRatio": "1.33"
    },
    {
      "file": "33a5f4b9-c902-4fec-a426-e52ee402eddd.jpg",
      "width": 1054,
      "height": 746,
      "orientation": "landscape",
      "aspectRatio": "1.41"
    },
    {
      "file": "37c88870-4eae-4a8b-84f1-2cf700e391cb.jpg",
      "width": 735,
      "height": 723,
      "orientation": "landscape",
      "aspectRatio": "1.02"
    },
    {
      "file": "43f4a7ae-c477-453d-898a-17816013ec22.jpg",
      "width": 1080,
      "height": 700,
      "orientation": "landscape",
      "aspectRatio": "1.54"
    },
    {
      "file": "447992a0-1577-46a7-9fe0-f83f5e47b23b.jpg",
      "width": 996,
      "height": 788,
      "orientation": "landscape",
      "aspectRatio": "1.26"
    },
    {
      "file": "4999f74e-c516-4308-949b-f777307de8d9.jpg",
      "width": 1024,
      "height": 768,
      "orientation": "landscape",
      "aspectRatio": "1.33"
    },
    {
      "file": "4f83425f-fb62-4c9c-88e7-9809dbaec2a6.jpg",
      "width": 836,
      "height": 553,
      "orientation": "landscape",
      "aspectRatio": "1.51"
    },
    {
      "file": "50765142-d7f9-4d0f-b74c-dec54377cc65.jpg",
      "width": 1023,
      "height": 731,
      "orientation": "landscape",
      "aspectRatio": "1.40"
    },
    {
      "file": "54cd29b8-34b8-4a31-a0c3-931c27a0c585.jpg",
      "width": 1284,
      "height": 1106,
      "orientation": "landscape",
      "aspectRatio": "1.16"
    },
    {
      "file": "65479075-526c-4f8a-985f-039cc9403da0.jpg",
      "width": 600,
      "height": 400,
      "orientation": "landscape",
      "aspectRatio": "1.50"
    },
    {
      "file": "743f6a27-5e72-484e-9619-b374effee2ef.jpg",
      "width": 1024,
      "height": 768,
      "orientation": "landscape",
      "aspectRatio": "1.33"
    },
    {
      "file": "74d050bb-97e3-441e-aa6e-f5f6b39fa7c7.jpg",
      "width": 803,
      "height": 535,
      "orientation": "landscape",
      "aspectRatio": "1.50"
    },
    {
      "file": "781221d3-5fd2-41f6-8129-c59e03643d3c.jpg",
      "width": 735,
      "height": 715,
      "orientation": "landscape",
      "aspectRatio": "1.03"
    },
    {
      "file": "78f40680-138e-4cfe-8ef7-159c0fb5821b.jpg",
      "width": 1024,
      "height": 768,
      "orientation": "landscape",
      "aspectRatio": "1.33"
    },
    {
      "file": "795bf32d-b851-48a5-9857-bcdc3e9ce14c.jpg",
      "width": 300,
      "height": 168,
      "orientation": "landscape",
      "aspectRatio": "1.79"
    },
    {
      "file": "8073dadb-306a-4997-af00-3d16977208c6.jpg",
      "width": 1074,
      "height": 732,
      "orientation": "landscape",
      "aspectRatio": "1.47"
    },
    {
      "file": "920724cd-3248-4bad-a94f-b7903d600e58.jpg",
      "width": 1366,
      "height": 1365,
      "orientation": "landscape",
      "aspectRatio": "1.00"
    },
    {
      "file": "96de4ad7-58b3-4847-8cbc-7e73d1e3fe68.jpg",
      "width": 1090,
      "height": 720,
      "orientation": "landscape",
      "aspectRatio": "1.51"
    },
    {
      "file": "98fc9eab-5526-42ae-8ea9-cc88d7f34f35.jpg",
      "width": 1024,
      "height": 607,
      "orientation": "landscape",
      "aspectRatio": "1.69"
    },
    {
      "file": "9c960da4-a666-46b8-9396-73fd45e76373.jpg",
      "width": 1086,
      "height": 725,
      "orientation": "landscape",
      "aspectRatio": "1.50"
    },
    {
      "file": "a7c7d916-c870-4615-928c-09a7c5a80ae1.jpg",
      "width": 1080,
      "height": 783,
      "orientation": "landscape",
      "aspectRatio": "1.38"
    },
    {
      "file": "a811ba7b-80b1-4c7d-884e-5aa7d687b24e.jpg",
      "width": 1024,
      "height": 768,
      "orientation": "landscape",
      "aspectRatio": "1.33"
    },
    {
      "file": "acecc917-9cd8-4039-92f5-95cf8951629f.jpg",
      "width": 400,
      "height": 301,
      "orientation": "landscape",
      "aspectRatio": "1.33"
    },
    {
      "file": "af436bac-31cf-44fc-a6f7-5e4eb5cca3f4.jpg",
      "width": 299,
      "height": 168,
      "orientation": "landscape",
      "aspectRatio": "1.78"
    },
    {
      "file": "b33f75d5-9268-40a7-9638-fb9ab4d577bd.jpg",
      "width": 1476,
      "height": 776,
      "orientation": "landscape",
      "aspectRatio": "1.90"
    },
    {
      "file": "b4b9e254-80df-42a5-9e3e-aead3df74dbb.jpg",
      "width": 1024,
      "height": 768,
      "orientation": "landscape",
      "aspectRatio": "1.33"
    },
    {
      "file": "b7a05597-289f-4219-93f2-f15d33c2b5b4.jpg",
      "width": 1024,
      "height": 768,
      "orientation": "landscape",
      "aspectRatio": "1.33"
    },
    {
      "file": "bd212f93-69b4-4f84-a740-d10fc9495783.jpg",
      "width": 1024,
      "height": 768,
      "orientation": "landscape",
      "aspectRatio": "1.33"
    },
    {
      "file": "bebe1d0f-dc63-4e39-99f7-1ffa38e0e4bb.jpg",
      "width": 1024,
      "height": 768,
      "orientation": "landscape",
      "aspectRatio": "1.33"
    },
    {
      "file": "cc8b3638-90c2-4ec9-ab62-234f411fd521.jpg",
      "width": 1200,
      "height": 675,
      "orientation": "landscape",
      "aspectRatio": "1.78"
    },
    {
      "file": "d0577f70-911d-4f25-b772-486bee500d32.jpg",
      "width": 1020,
      "height": 671,
      "orientation": "landscape",
      "aspectRatio": "1.52"
    },
    {
      "file": "d4945318-3353-434b-bc48-68dc3ce8f125.jpg",
      "width": 1092,
      "height": 719,
      "orientation": "landscape",
      "aspectRatio": "1.52"
    },
    {
      "file": "dcdebdac-15ee-402f-909a-eb0d4852aa83.jpg",
      "width": 500,
      "height": 411,
      "orientation": "landscape",
      "aspectRatio": "1.22"
    },
    {
      "file": "e66f2efb-d477-48c3-abbf-55b5cf62049f.jpg",
      "width": 1024,
      "height": 768,
      "orientation": "landscape",
      "aspectRatio": "1.33"
    },
    {
      "file": "f5db8488-814d-4a51-af36-225ffbed4b00.jpg",
      "width": 1020,
      "height": 671,
      "orientation": "landscape",
      "aspectRatio": "1.52"
    }
  ],
  "portrait": [
    {
      "file": "00b85d32-960a-4d53-a422-e111c1243adf.jpg",
      "width": 768,
      "height": 1024,
      "orientation": "portrait",
      "aspectRatio": "0.75"
    },
    {
      "file": "02dc6d0a-92fb-42f3-9e90-8e831d15b7fe.jpg",
      "width": 800,
      "height": 1000,
      "orientation": "portrait",
      "aspectRatio": "0.80"
    },
    {
      "file": "02f48fd0-477b-4050-a1ef-fc6eb402281b.jpg",
      "width": 1200,
      "height": 1600,
      "orientation": "portrait",
      "aspectRatio": "0.75"
    },
    {
      "file": "0416155e-08c4-48fa-b85f-ffe994ad9219.jpg",
      "width": 768,
      "height": 1024,
      "orientation": "portrait",
      "aspectRatio": "0.75"
    },
    {
      "file": "06d3ceec-01fe-4177-97ea-46780c6b3476.jpg",
      "width": 768,
      "height": 1024,
      "orientation": "portrait",
      "aspectRatio": "0.75"
    },
    {
      "file": "079f51de-c5a9-48f9-9df4-54d71aac383d.jpg",
      "width": 800,
      "height": 1000,
      "orientation": "portrait",
      "aspectRatio": "0.80"
    },
    {
      "file": "07d39f7d-3065-4f4f-b066-0075cdcf252c.jpg",
      "width": 1200,
      "height": 1600,
      "orientation": "portrait",
      "aspectRatio": "0.75"
    },
    {
      "file": "0e8e0f80-d6b3-4eeb-8e2a-1b93f2190387.jpg",
      "width": 517,
      "height": 1520,
      "orientation": "portrait",
      "aspectRatio": "0.34"
    },
    {
      "file": "0fc7baa8-06b2-45aa-aa3a-ac60312ab00b.jpg",
      "width": 768,
      "height": 1024,
      "orientation": "portrait",
      "aspectRatio": "0.75"
    },
    {
      "file": "0fd2b846-1f54-4bac-b433-7d42a5c8db9a.jpg",
      "width": 768,
      "height": 1024,
      "orientation": "portrait",
      "aspectRatio": "0.75"
    },
    {
      "file": "11dce202-3b3d-4102-a071-8a30423f2e83.jpg",
      "width": 1170,
      "height": 1360,
      "orientation": "portrait",
      "aspectRatio": "0.86"
    },
    {
      "file": "11e48d7e-c13c-4a16-adc4-4209b370e3ed.jpg",
      "width": 768,
      "height": 1024,
      "orientation": "portrait",
      "aspectRatio": "0.75"
    },
    {
      "file": "1428bac1-bb24-47f3-b9d0-41912b11624d.jpg",
      "width": 768,
      "height": 1024,
      "orientation": "portrait",
      "aspectRatio": "0.75"
    },
    {
      "file": "1598ca83-e37f-497f-8bc9-9b9cc6fc59f7.jpg",
      "width": 768,
      "height": 1024,
      "orientation": "portrait",
      "aspectRatio": "0.75"
    },
    {
      "file": "15ab5aa5-396e-4373-8af0-fd98828e05f3.jpg",
      "width": 1200,
      "height": 1600,
      "orientation": "portrait",
      "aspectRatio": "0.75"
    },
    {
      "file": "1602fc18-6cfe-44ea-a11d-190d175e4874.jpg",
      "width": 1200,
      "height": 1600,
      "orientation": "portrait",
      "aspectRatio": "0.75"
    },
    {
      "file": "164b784f-ef1b-481c-bbda-0d3eb54a3053.jpg",
      "width": 1200,
      "height": 1600,
      "orientation": "portrait",
      "aspectRatio": "0.75"
    },
    {
      "file": "187cc953-4a4f-4434-a8db-f55104021b06.jpg",
      "width": 768,
      "height": 1024,
      "orientation": "portrait",
      "aspectRatio": "0.75"
    },
    {
      "file": "1eadde67-ad31-4a6b-8130-f968ff1c4407.jpg",
      "width": 768,
      "height": 1024,
      "orientation": "portrait",
      "aspectRatio": "0.75"
    },
    {
      "file": "1f8279b7-1994-4024-be84-6b014cd7a85e.jpg",
      "width": 768,
      "height": 1024,
      "orientation": "portrait",
      "aspectRatio": "0.75"
    },
    {
      "file": "1fc976a8-08e7-49e7-82d9-97ab7b942dab.jpg",
      "width": 768,
      "height": 1024,
      "orientation": "portrait",
      "aspectRatio": "0.75"
    },
    {
      "file": "2068d223-4bcf-4f84-976f-2c0b96627496.jpg",
      "width": 768,
      "height": 1024,
      "orientation": "portrait",
      "aspectRatio": "0.75"
    },
    {
      "file": "20a02e79-8b74-4bdb-906d-1cb4e4626a22.jpg",
      "width": 800,
      "height": 1000,
      "orientation": "portrait",
      "aspectRatio": "0.80"
    },
    {
      "file": "20e2a3ea-e7cc-4737-b668-0bd3f6f30dcc.jpg",
      "width": 1200,
      "height": 1600,
      "orientation": "portrait",
      "aspectRatio": "0.75"
    },
    {
      "file": "212d0904-2c9f-4391-a5f6-b7ad6615377d.jpg",
      "width": 768,
      "height": 1024,
      "orientation": "portrait",
      "aspectRatio": "0.75"
    },
    {
      "file": "22e69919-4b7a-4e80-9dc6-b09cf69b34a3.jpg",
      "width": 768,
      "height": 1024,
      "orientation": "portrait",
      "aspectRatio": "0.75"
    },
    {
      "file": "240d6e79-f404-449c-a0dc-f4a18d6f148d.jpg",
      "width": 768,
      "height": 1024,
      "orientation": "portrait",
      "aspectRatio": "0.75"
    },
    {
      "file": "2472fd09-3839-487d-a96a-b78c92ea754c.jpg",
      "width": 1066,
      "height": 1600,
      "orientation": "portrait",
      "aspectRatio": "0.67"
    },
    {
      "file": "249e0b02-2f8b-4b8e-880d-630bd81f00c0.jpg",
      "width": 768,
      "height": 1024,
      "orientation": "portrait",
      "aspectRatio": "0.75"
    },
    {
      "file": "24dbf7e4-8dd1-444b-badd-f7fcd9239cc8.jpg",
      "width": 1200,
      "height": 1600,
      "orientation": "portrait",
      "aspectRatio": "0.75"
    },
    {
      "file": "274c8439-d1d0-4c28-b85c-0dbf3f77ac37.jpg",
      "width": 1200,
      "height": 1600,
      "orientation": "portrait",
      "aspectRatio": "0.75"
    },
    {
      "file": "2845408b-3dc2-486c-9e49-a0c8ab6bc140.jpg",
      "width": 738,
      "height": 1600,
      "orientation": "portrait",
      "aspectRatio": "0.46"
    },
    {
      "file": "291bd8ac-71fc-4261-90d7-d92a411d458b.jpg",
      "width": 768,
      "height": 1024,
      "orientation": "portrait",
      "aspectRatio": "0.75"
    },
    {
      "file": "2b0b0327-5e47-4f21-8267-9f84ebca1f98.jpg",
      "width": 1200,
      "height": 1600,
      "orientation": "portrait",
      "aspectRatio": "0.75"
    },
    {
      "file": "2dbf852d-7096-4027-996f-531f728d0f71.jpg",
      "width": 768,
      "height": 1024,
      "orientation": "portrait",
      "aspectRatio": "0.75"
    },
    {
      "file": "2efa769f-0bd7-48ec-b101-f541a9fb48ca.jpg",
      "width": 1170,
      "height": 1452,
      "orientation": "portrait",
      "aspectRatio": "0.81"
    },
    {
      "file": "31bd82fb-fd0c-4a62-8105-34f6b8cf0814.jpg",
      "width": 768,
      "height": 1024,
      "orientation": "portrait",
      "aspectRatio": "0.75"
    },
    {
      "file": "3403992d-c0f2-4f08-8613-ec242a92de37.jpg",
      "width": 768,
      "height": 1024,
      "orientation": "portrait",
      "aspectRatio": "0.75"
    },
    {
      "file": "35632645-a8e4-4c92-bd64-ccef1ccf6697.jpg",
      "width": 768,
      "height": 1024,
      "orientation": "portrait",
      "aspectRatio": "0.75"
    },
    {
      "file": "37eb2690-f823-4b47-b12c-9d9b78d5db97.jpg",
      "width": 768,
      "height": 1024,
      "orientation": "portrait",
      "aspectRatio": "0.75"
    },
    {
      "file": "397d0dd2-5e66-4c2a-8217-af4e0cb2dbc5.jpg",
      "width": 768,
      "height": 1024,
      "orientation": "portrait",
      "aspectRatio": "0.75"
    },
    {
      "file": "39fb053d-9cf9-42ac-8148-09e1d76248e8.jpg",
      "width": 1200,
      "height": 1600,
      "orientation": "portrait",
      "aspectRatio": "0.75"
    },
    {
      "file": "3a05ef07-e570-47a7-a92a-d4d710520848.jpg",
      "width": 768,
      "height": 1024,
      "orientation": "portrait",
      "aspectRatio": "0.75"
    },
    {
      "file": "3bb1d910-7134-4c7f-b536-9533bc992c83.jpg",
      "width": 768,
      "height": 1024,
      "orientation": "portrait",
      "aspectRatio": "0.75"
    },
    {
      "file": "3d576ad2-9bfc-4941-b09f-66135ec2f9c9.jpg",
      "width": 768,
      "height": 1024,
      "orientation": "portrait",
      "aspectRatio": "0.75"
    },
    {
      "file": "3dd9dae6-4e51-44d9-bd47-334f05a6e830.jpg",
      "width": 768,
      "height": 1024,
      "orientation": "portrait",
      "aspectRatio": "0.75"
    },
    {
      "file": "3f30d978-0095-48e1-85cc-50fa5d149354.jpg",
      "width": 768,
      "height": 1024,
      "orientation": "portrait",
      "aspectRatio": "0.75"
    },
    {
      "file": "3f8a6fa1-80c7-457f-bfba-2a4cb619bb28.jpg",
      "width": 768,
      "height": 1024,
      "orientation": "portrait",
      "aspectRatio": "0.75"
    },
    {
      "file": "4076b71a-1c40-449a-aa4b-65676441483c.jpg",
      "width": 1200,
      "height": 1600,
      "orientation": "portrait",
      "aspectRatio": "0.75"
    },
    {
      "file": "447c3890-7518-422e-afa3-1d89e1d6964b.jpg",
      "width": 400,
      "height": 400,
      "orientation": "portrait",
      "aspectRatio": "1.00"
    },
    {
      "file": "44b02d9a-23d5-445d-9ad6-af1dd4316383.jpg",
      "width": 768,
      "height": 1024,
      "orientation": "portrait",
      "aspectRatio": "0.75"
    },
    {
      "file": "466155fd-a55a-4f03-95da-ade7025a347e.jpg",
      "width": 1200,
      "height": 1600,
      "orientation": "portrait",
      "aspectRatio": "0.75"
    },
    {
      "file": "48cc9ed3-7ade-4806-b7ff-e71f1ce76e0d.jpg",
      "width": 768,
      "height": 1024,
      "orientation": "portrait",
      "aspectRatio": "0.75"
    },
    {
      "file": "49ca4c7d-4d1f-43df-a93d-d000f0e1cbf2.jpg",
      "width": 1200,
      "height": 1600,
      "orientation": "portrait",
      "aspectRatio": "0.75"
    },
    {
      "file": "49f6cc49-5c19-4fc8-b23d-8e0859891e4a.jpg",
      "width": 768,
      "height": 1024,
      "orientation": "portrait",
      "aspectRatio": "0.75"
    },
    {
      "file": "4aae3c2d-8077-4f26-9907-0bbd12877a91.jpg",
      "width": 1200,
      "height": 1600,
      "orientation": "portrait",
      "aspectRatio": "0.75"
    },
    {
      "file": "4ace8804-9400-4620-a954-799cecc7035f.jpg",
      "width": 1200,
      "height": 1600,
      "orientation": "portrait",
      "aspectRatio": "0.75"
    },
    {
      "file": "4b5ec452-6a2f-461a-a228-0a0b53ddf744.jpg",
      "width": 768,
      "height": 1024,
      "orientation": "portrait",
      "aspectRatio": "0.75"
    },
    {
      "file": "4ddedf6e-9dad-44a9-a641-99c8409262a9.jpg",
      "width": 1200,
      "height": 1600,
      "orientation": "portrait",
      "aspectRatio": "0.75"
    },
    {
      "file": "4df32565-e013-4de0-b6d0-5ff238a16ee5.jpg",
      "width": 800,
      "height": 1000,
      "orientation": "portrait",
      "aspectRatio": "0.80"
    },
    {
      "file": "4df910d9-6769-4464-b199-afb3fed93ed1.jpg",
      "width": 768,
      "height": 1024,
      "orientation": "portrait",
      "aspectRatio": "0.75"
    },
    {
      "file": "4e580e4a-9a61-446d-8042-e0dacb406e60.jpg",
      "width": 1200,
      "height": 1600,
      "orientation": "portrait",
      "aspectRatio": "0.75"
    },
    {
      "file": "4eae488e-88bc-4378-b283-709619cf8297.jpg",
      "width": 514,
      "height": 680,
      "orientation": "portrait",
      "aspectRatio": "0.76"
    },
    {
      "file": "4f7c841c-64f1-40c0-a78a-8239f5eee5a6.jpg",
      "width": 768,
      "height": 1024,
      "orientation": "portrait",
      "aspectRatio": "0.75"
    },
    {
      "file": "507bcbc9-a630-4be9-affc-4c7a8b2fc54a.jpg",
      "width": 768,
      "height": 1024,
      "orientation": "portrait",
      "aspectRatio": "0.75"
    },
    {
      "file": "51c18b73-d04d-4d31-bb0c-d971a033b959.jpg",
      "width": 768,
      "height": 1024,
      "orientation": "portrait",
      "aspectRatio": "0.75"
    },
    {
      "file": "52e6979b-a1dc-4677-954b-98d0a194e9c6.jpg",
      "width": 768,
      "height": 1024,
      "orientation": "portrait",
      "aspectRatio": "0.75"
    },
    {
      "file": "53c346f4-036e-4992-b44a-6b437c406979.jpg",
      "width": 768,
      "height": 1024,
      "orientation": "portrait",
      "aspectRatio": "0.75"
    },
    {
      "file": "53f12730-7404-46d9-86eb-1e96fa5e8793.jpg",
      "width": 768,
      "height": 1024,
      "orientation": "portrait",
      "aspectRatio": "0.75"
    },
    {
      "file": "582857bc-ce99-4a36-91a4-a3ddb158e9db.jpg",
      "width": 768,
      "height": 1024,
      "orientation": "portrait",
      "aspectRatio": "0.75"
    },
    {
      "file": "5889dd0e-577f-4a57-93e6-7f6775410946.jpg",
      "width": 768,
      "height": 1024,
      "orientation": "portrait",
      "aspectRatio": "0.75"
    },
    {
      "file": "59617592-805c-478f-b2d3-f3cdaa051be5.jpg",
      "width": 768,
      "height": 1024,
      "orientation": "portrait",
      "aspectRatio": "0.75"
    },
    {
      "file": "5a530faa-ec6a-4e59-a7f3-4b8ff7d4ae3a.jpg",
      "width": 768,
      "height": 1024,
      "orientation": "portrait",
      "aspectRatio": "0.75"
    },
    {
      "file": "5b00b950-73b6-4618-b7b8-1a90427e778e.jpg",
      "width": 768,
      "height": 1024,
      "orientation": "portrait",
      "aspectRatio": "0.75"
    },
    {
      "file": "5b679560-ff91-4e0f-b780-c84f4483eaa8.jpg",
      "width": 768,
      "height": 1024,
      "orientation": "portrait",
      "aspectRatio": "0.75"
    },
    {
      "file": "5dcfae74-21f6-4bff-bbe9-fa82ad3b8f20.jpg",
      "width": 768,
      "height": 1024,
      "orientation": "portrait",
      "aspectRatio": "0.75"
    },
    {
      "file": "5e79374f-8fb3-4b71-9a32-9649d47232a0.jpg",
      "width": 768,
      "height": 1024,
      "orientation": "portrait",
      "aspectRatio": "0.75"
    },
    {
      "file": "60f2ef0e-5a0b-44dd-aced-d402020d65b4.jpg",
      "width": 886,
      "height": 886,
      "orientation": "portrait",
      "aspectRatio": "1.00"
    },
    {
      "file": "613629ce-a3ca-4776-aa49-a11bcf4eb3f7.jpg",
      "width": 1200,
      "height": 1600,
      "orientation": "portrait",
      "aspectRatio": "0.75"
    },
    {
      "file": "629db76b-fdb4-4e6d-8852-f7c804dd971e.jpg",
      "width": 768,
      "height": 1024,
      "orientation": "portrait",
      "aspectRatio": "0.75"
    },
    {
      "file": "64581a21-1e72-4cad-a24f-06049108a425.jpg",
      "width": 768,
      "height": 1024,
      "orientation": "portrait",
      "aspectRatio": "0.75"
    },
    {
      "file": "64d519d5-53db-44b3-8fa7-29f2181c209b.jpg",
      "width": 1200,
      "height": 1600,
      "orientation": "portrait",
      "aspectRatio": "0.75"
    },
    {
      "file": "68a27fd5-416e-44e7-a5b5-bbec8de7672a.jpg",
      "width": 768,
      "height": 1024,
      "orientation": "portrait",
      "aspectRatio": "0.75"
    },
    {
      "file": "6cc9a04d-dda8-4204-b045-57596749fb42.jpg",
      "width": 768,
      "height": 1024,
      "orientation": "portrait",
      "aspectRatio": "0.75"
    },
    {
      "file": "6cfc0d62-fa4d-4f61-b015-82b05070e4cb.jpg",
      "width": 768,
      "height": 1024,
      "orientation": "portrait",
      "aspectRatio": "0.75"
    },
    {
      "file": "6d7390a0-cae4-4120-a6bc-76125c6b56b7.jpg",
      "width": 768,
      "height": 1024,
      "orientation": "portrait",
      "aspectRatio": "0.75"
    },
    {
      "file": "6f32997d-cccf-4028-a107-fc1ffaccaff0.jpg",
      "width": 768,
      "height": 1024,
      "orientation": "portrait",
      "aspectRatio": "0.75"
    },
    {
      "file": "73e43382-28e2-4902-b759-532cb115d265.jpg",
      "width": 768,
      "height": 1024,
      "orientation": "portrait",
      "aspectRatio": "0.75"
    },
    {
      "file": "742ce1b8-dc18-4ba5-9322-bf8fa3677e7c.jpg",
      "width": 768,
      "height": 1024,
      "orientation": "portrait",
      "aspectRatio": "0.75"
    },
    {
      "file": "76e33d10-1a89-4c3d-9588-58e31802f156.jpg",
      "width": 768,
      "height": 1024,
      "orientation": "portrait",
      "aspectRatio": "0.75"
    },
    {
      "file": "77191a9a-5c75-4af7-9603-791ceed45dc5.jpg",
      "width": 768,
      "height": 1024,
      "orientation": "portrait",
      "aspectRatio": "0.75"
    },
    {
      "file": "78f7a750-1c98-4ce4-b2b3-972734b30075.jpg",
      "width": 1200,
      "height": 1600,
      "orientation": "portrait",
      "aspectRatio": "0.75"
    },
    {
      "file": "797131f7-61b2-4a8f-a8bd-dae8e98d669e.jpg",
      "width": 1200,
      "height": 1600,
      "orientation": "portrait",
      "aspectRatio": "0.75"
    },
    {
      "file": "7b2b2878-877f-4dad-92a0-3d678aff19d0.jpg",
      "width": 768,
      "height": 1024,
      "orientation": "portrait",
      "aspectRatio": "0.75"
    },
    {
      "file": "7b3032a9-0e7f-406f-9093-cef56fdb7dc9.jpg",
      "width": 768,
      "height": 1024,
      "orientation": "portrait",
      "aspectRatio": "0.75"
    },
    {
      "file": "7bdeef21-bac2-464e-9651-4f0f129b487d.jpg",
      "width": 768,
      "height": 1024,
      "orientation": "portrait",
      "aspectRatio": "0.75"
    },
    {
      "file": "7d4a941f-662e-4ea0-a28b-203a742e4bd4.jpg",
      "width": 1200,
      "height": 1600,
      "orientation": "portrait",
      "aspectRatio": "0.75"
    },
    {
      "file": "7dca323d-bc8f-42af-9a94-dfb1b1eb8f24.jpg",
      "width": 736,
      "height": 914,
      "orientation": "portrait",
      "aspectRatio": "0.81"
    },
    {
      "file": "7e5d5c6c-8c6c-4e88-98a7-42a345964c29.jpg",
      "width": 768,
      "height": 1024,
      "orientation": "portrait",
      "aspectRatio": "0.75"
    },
    {
      "file": "7f12b711-926f-4bec-9088-f9d5bcd3e4f0.jpg",
      "width": 768,
      "height": 1024,
      "orientation": "portrait",
      "aspectRatio": "0.75"
    },
    {
      "file": "7fa69f80-3828-4f3e-bef8-95891c95174f.jpg",
      "width": 1200,
      "height": 1600,
      "orientation": "portrait",
      "aspectRatio": "0.75"
    },
    {
      "file": "7fdfd363-2ad4-4566-aaa6-730567a5ba67.jpg",
      "width": 768,
      "height": 1024,
      "orientation": "portrait",
      "aspectRatio": "0.75"
    },
    {
      "file": "8007ec80-1c7e-419e-94b3-8ecdd7185e27.jpg",
      "width": 768,
      "height": 1024,
      "orientation": "portrait",
      "aspectRatio": "0.75"
    },
    {
      "file": "82e1478f-ec54-4058-a3cd-2fdcf62c5362.jpg",
      "width": 768,
      "height": 1024,
      "orientation": "portrait",
      "aspectRatio": "0.75"
    },
    {
      "file": "833621e1-776f-4998-a402-214770ccd94f.jpg",
      "width": 768,
      "height": 1024,
      "orientation": "portrait",
      "aspectRatio": "0.75"
    },
    {
      "file": "854937d1-e3ef-4abc-acb2-3c277792548f.jpg",
      "width": 768,
      "height": 1024,
      "orientation": "portrait",
      "aspectRatio": "0.75"
    },
    {
      "file": "855ee5e0-6a44-40c4-af76-8406a9154787.jpg",
      "width": 768,
      "height": 1024,
      "orientation": "portrait",
      "aspectRatio": "0.75"
    },
    {
      "file": "88b9e2c5-f62a-4928-b2bb-b979d0846bab.jpg",
      "width": 768,
      "height": 1024,
      "orientation": "portrait",
      "aspectRatio": "0.75"
    },
    {
      "file": "88c6f03e-7476-426d-965f-ff9289c33fed.jpg",
      "width": 768,
      "height": 1024,
      "orientation": "portrait",
      "aspectRatio": "0.75"
    },
    {
      "file": "89b29843-a7a3-40b9-8308-0f9ad659e0fe.jpg",
      "width": 1200,
      "height": 1600,
      "orientation": "portrait",
      "aspectRatio": "0.75"
    },
    {
      "file": "8b62d923-e3bc-4a14-a74a-4ce6b12d9416.jpg",
      "width": 768,
      "height": 1024,
      "orientation": "portrait",
      "aspectRatio": "0.75"
    },
    {
      "file": "8d9a2862-eff1-4e7e-acc3-ced45852e041.jpg",
      "width": 768,
      "height": 1024,
      "orientation": "portrait",
      "aspectRatio": "0.75"
    },
    {
      "file": "9727a449-c812-4cfa-a116-14a8c1ca2a92.jpg",
      "width": 1600,
      "height": 1600,
      "orientation": "portrait",
      "aspectRatio": "1.00"
    },
    {
      "file": "99ef7ece-69ce-46c0-9198-41aa16961b1a.jpg",
      "width": 802,
      "height": 810,
      "orientation": "portrait",
      "aspectRatio": "0.99"
    },
    {
      "file": "9b72eb47-baa2-4e3b-8a82-c8655edbbec9.jpg",
      "width": 768,
      "height": 1024,
      "orientation": "portrait",
      "aspectRatio": "0.75"
    },
    {
      "file": "9d10f53b-a7f4-4122-8e6f-9970149febff.jpg",
      "width": 1200,
      "height": 1600,
      "orientation": "portrait",
      "aspectRatio": "0.75"
    },
    {
      "file": "9d6ced7f-44db-4f2b-adf6-b6fc6cd49737.jpg",
      "width": 768,
      "height": 1024,
      "orientation": "portrait",
      "aspectRatio": "0.75"
    },
    {
      "file": "9d9a63a9-463b-4cf8-b4e1-52d6236a6dc2.jpg",
      "width": 768,
      "height": 1024,
      "orientation": "portrait",
      "aspectRatio": "0.75"
    },
    {
      "file": "a04baec1-9ab4-462a-9a62-125be2e5fb40.jpg",
      "width": 768,
      "height": 1024,
      "orientation": "portrait",
      "aspectRatio": "0.75"
    },
    {
      "file": "a05821a3-4b74-4973-adef-3de618b41808.jpg",
      "width": 1200,
      "height": 1600,
      "orientation": "portrait",
      "aspectRatio": "0.75"
    },
    {
      "file": "a45a560b-8696-4687-a954-deb458a21c8c.jpg",
      "width": 768,
      "height": 1024,
      "orientation": "portrait",
      "aspectRatio": "0.75"
    },
    {
      "file": "a560fc39-a436-4d61-9041-b0514d9ad150.jpg",
      "width": 768,
      "height": 1024,
      "orientation": "portrait",
      "aspectRatio": "0.75"
    },
    {
      "file": "a7d3f0d2-df35-4ceb-9ed4-7c6aedc8f1c3.jpg",
      "width": 831,
      "height": 946,
      "orientation": "portrait",
      "aspectRatio": "0.88"
    },
    {
      "file": "a7f1cec0-75ed-4e96-8f11-a18412c5654d.jpg",
      "width": 768,
      "height": 1024,
      "orientation": "portrait",
      "aspectRatio": "0.75"
    },
    {
      "file": "a87ec457-d043-44bf-b093-43abae276e5b.jpg",
      "width": 768,
      "height": 1024,
      "orientation": "portrait",
      "aspectRatio": "0.75"
    },
    {
      "file": "a9500c20-eca4-4cd1-9338-85c28e53efa6.jpg",
      "width": 768,
      "height": 1024,
      "orientation": "portrait",
      "aspectRatio": "0.75"
    },
    {
      "file": "a9f07013-a76a-4952-b7ca-3e5e936c769e.jpg",
      "width": 768,
      "height": 1024,
      "orientation": "portrait",
      "aspectRatio": "0.75"
    },
    {
      "file": "aa521b90-9e30-4a39-a5bf-47b300d63f01.jpg",
      "width": 768,
      "height": 1024,
      "orientation": "portrait",
      "aspectRatio": "0.75"
    },
    {
      "file": "abe8c820-6102-4da2-8168-9775a90fcb10.jpg",
      "width": 768,
      "height": 1024,
      "orientation": "portrait",
      "aspectRatio": "0.75"
    },
    {
      "file": "acac8d5c-677f-4ea9-9d37-aade5cab3070.jpg",
      "width": 1200,
      "height": 1600,
      "orientation": "portrait",
      "aspectRatio": "0.75"
    },
    {
      "file": "ae2f655a-e14e-4fd7-b14b-f457b78e65fb.jpg",
      "width": 768,
      "height": 1024,
      "orientation": "portrait",
      "aspectRatio": "0.75"
    },
    {
      "file": "afa26cb4-839d-440b-8973-fd5a0255571f.jpg",
      "width": 768,
      "height": 1024,
      "orientation": "portrait",
      "aspectRatio": "0.75"
    },
    {
      "file": "b0161976-2246-4c07-a998-5dcdf81e5de5.jpg",
      "width": 1200,
      "height": 1600,
      "orientation": "portrait",
      "aspectRatio": "0.75"
    },
    {
      "file": "b0307d59-4fba-4cc5-89c1-e3f6cfe44a18.jpg",
      "width": 768,
      "height": 1024,
      "orientation": "portrait",
      "aspectRatio": "0.75"
    },
    {
      "file": "b07a9020-9603-4fa4-8fbc-e63c72b53c16.jpg",
      "width": 826,
      "height": 950,
      "orientation": "portrait",
      "aspectRatio": "0.87"
    },
    {
      "file": "b1d84fcd-6f7c-433e-9212-5251fa5df784.jpg",
      "width": 768,
      "height": 1024,
      "orientation": "portrait",
      "aspectRatio": "0.75"
    },
    {
      "file": "b36f0494-bcfc-4b5f-aad1-682fce0e260d.jpg",
      "width": 1280,
      "height": 1600,
      "orientation": "portrait",
      "aspectRatio": "0.80"
    },
    {
      "file": "b3978510-f4e0-4a14-bc3c-fab809f6de1d.jpg",
      "width": 1200,
      "height": 1600,
      "orientation": "portrait",
      "aspectRatio": "0.75"
    },
    {
      "file": "b4ec8098-02e2-4fc5-bfa8-876070affdc0.jpg",
      "width": 800,
      "height": 1000,
      "orientation": "portrait",
      "aspectRatio": "0.80"
    },
    {
      "file": "b5097946-e146-4d4c-8488-8dd217f32654.jpg",
      "width": 1200,
      "height": 1600,
      "orientation": "portrait",
      "aspectRatio": "0.75"
    },
    {
      "file": "b55e2bbd-bb7e-43c9-8ab0-02cc2d282e84.jpg",
      "width": 1143,
      "height": 1600,
      "orientation": "portrait",
      "aspectRatio": "0.71"
    },
    {
      "file": "b586b88c-acea-4d00-b67e-115b49751066.jpg",
      "width": 768,
      "height": 1024,
      "orientation": "portrait",
      "aspectRatio": "0.75"
    },
    {
      "file": "b78328c2-fda7-4864-815e-e11c3c0facf8.jpg",
      "width": 768,
      "height": 1024,
      "orientation": "portrait",
      "aspectRatio": "0.75"
    },
    {
      "file": "b78db480-40d2-4478-acbc-7552cc2610e4.jpg",
      "width": 766,
      "height": 1028,
      "orientation": "portrait",
      "aspectRatio": "0.75"
    },
    {
      "file": "b833cc54-0cbd-4349-8610-43ff577606d3.jpg",
      "width": 819,
      "height": 1024,
      "orientation": "portrait",
      "aspectRatio": "0.80"
    },
    {
      "file": "b988a37e-0684-4b1d-8dc5-7d47c5daf893.jpg",
      "width": 768,
      "height": 1024,
      "orientation": "portrait",
      "aspectRatio": "0.75"
    },
    {
      "file": "b9e502be-12db-41d3-afb7-bfef47181c2a.jpg",
      "width": 768,
      "height": 1024,
      "orientation": "portrait",
      "aspectRatio": "0.75"
    },
    {
      "file": "bf094915-6bcc-42fe-8e24-1005fa98843f.jpg",
      "width": 965,
      "height": 966,
      "orientation": "portrait",
      "aspectRatio": "1.00"
    },
    {
      "file": "c199634a-d996-413b-87c5-06e78e6d55b9.jpg",
      "width": 768,
      "height": 1024,
      "orientation": "portrait",
      "aspectRatio": "0.75"
    },
    {
      "file": "c22db1f9-b884-4d83-ab8e-ca909e353c18.jpg",
      "width": 1200,
      "height": 1600,
      "orientation": "portrait",
      "aspectRatio": "0.75"
    },
    {
      "file": "c32c27ff-c087-4af0-b18a-0dd57b85e868.jpg",
      "width": 768,
      "height": 1024,
      "orientation": "portrait",
      "aspectRatio": "0.75"
    },
    {
      "file": "c399a41b-cd9b-46bb-a816-b1c983d6d4ac.jpg",
      "width": 791,
      "height": 992,
      "orientation": "portrait",
      "aspectRatio": "0.80"
    },
    {
      "file": "c3cda0ed-2ad2-4c93-899f-2de91142ae4d.jpg",
      "width": 1000,
      "height": 1000,
      "orientation": "portrait",
      "aspectRatio": "1.00"
    },
    {
      "file": "c47455aa-d930-47af-a473-f5ebe243f4e2.jpg",
      "width": 768,
      "height": 1024,
      "orientation": "portrait",
      "aspectRatio": "0.75"
    },
    {
      "file": "c7982ca7-6186-4397-aea5-ddfcd7f891fe.jpg",
      "width": 768,
      "height": 1024,
      "orientation": "portrait",
      "aspectRatio": "0.75"
    },
    {
      "file": "c7d76476-3d58-4159-9009-d755faa9b4cc.jpg",
      "width": 768,
      "height": 1024,
      "orientation": "portrait",
      "aspectRatio": "0.75"
    },
    {
      "file": "c83ed8e6-0984-446d-95a0-215926408238.jpg",
      "width": 768,
      "height": 1024,
      "orientation": "portrait",
      "aspectRatio": "0.75"
    },
    {
      "file": "c947f688-7acf-4dae-aeb9-c611d26d09b5.jpg",
      "width": 768,
      "height": 1024,
      "orientation": "portrait",
      "aspectRatio": "0.75"
    },
    {
      "file": "cbccf155-2f40-480d-bab4-7c9325d7f0b3.jpg",
      "width": 1200,
      "height": 1600,
      "orientation": "portrait",
      "aspectRatio": "0.75"
    },
    {
      "file": "d34a52f0-766d-4fdd-a5c5-f5f71182ca93.jpg",
      "width": 1200,
      "height": 1600,
      "orientation": "portrait",
      "aspectRatio": "0.75"
    },
    {
      "file": "d653f8b9-1a54-4d66-947d-051545f0ca22.jpg",
      "width": 1216,
      "height": 1600,
      "orientation": "portrait",
      "aspectRatio": "0.76"
    },
    {
      "file": "d70c0b42-3f15-4d26-82e8-29f94c68b7b7.jpg",
      "width": 675,
      "height": 900,
      "orientation": "portrait",
      "aspectRatio": "0.75"
    },
    {
      "file": "d7ab0b86-9040-436f-ba95-5a8c78a0a9fe.jpg",
      "width": 1200,
      "height": 1600,
      "orientation": "portrait",
      "aspectRatio": "0.75"
    },
    {
      "file": "d85bc8b2-4719-4fdc-878c-7ca7fe79040e.jpg",
      "width": 768,
      "height": 1024,
      "orientation": "portrait",
      "aspectRatio": "0.75"
    },
    {
      "file": "d87698ef-1e4b-4401-8f23-b1996c44a209.jpg",
      "width": 800,
      "height": 976,
      "orientation": "portrait",
      "aspectRatio": "0.82"
    },
    {
      "file": "d909fc38-7fa2-4322-b904-8e60a41554cf.jpg",
      "width": 768,
      "height": 1024,
      "orientation": "portrait",
      "aspectRatio": "0.75"
    },
    {
      "file": "d93a2b53-c432-4d24-8296-86fcae7dcc2b.jpg",
      "width": 1200,
      "height": 1600,
      "orientation": "portrait",
      "aspectRatio": "0.75"
    },
    {
      "file": "d9d30973-f426-42aa-b2b5-4e972a4e3dcd.jpg",
      "width": 1200,
      "height": 1600,
      "orientation": "portrait",
      "aspectRatio": "0.75"
    },
    {
      "file": "d9e8add9-da50-459d-b0e0-1561db397a71.jpg",
      "width": 1200,
      "height": 1600,
      "orientation": "portrait",
      "aspectRatio": "0.75"
    },
    {
      "file": "da1cdd31-390b-42e4-95ad-e57a12b78fda.jpg",
      "width": 768,
      "height": 1024,
      "orientation": "portrait",
      "aspectRatio": "0.75"
    },
    {
      "file": "dcb1e0d0-305e-4c5b-8331-1173759d6eae.jpg",
      "width": 768,
      "height": 1024,
      "orientation": "portrait",
      "aspectRatio": "0.75"
    },
    {
      "file": "dce11e8d-9dfd-4669-9c52-3674677a9501.jpg",
      "width": 768,
      "height": 1024,
      "orientation": "portrait",
      "aspectRatio": "0.75"
    },
    {
      "file": "dce37192-5ad4-42a0-bc71-b6fc8e31d256.jpg",
      "width": 1200,
      "height": 1600,
      "orientation": "portrait",
      "aspectRatio": "0.75"
    },
    {
      "file": "dd33ed78-10b2-4d13-b4fa-897a72a3ee02.jpg",
      "width": 1200,
      "height": 1600,
      "orientation": "portrait",
      "aspectRatio": "0.75"
    },
    {
      "file": "ddee72a6-1380-4d02-bf42-993667c06056.jpg",
      "width": 768,
      "height": 1024,
      "orientation": "portrait",
      "aspectRatio": "0.75"
    },
    {
      "file": "dec80c33-728c-46df-b6bc-144177abb996.jpg",
      "width": 1200,
      "height": 1600,
      "orientation": "portrait",
      "aspectRatio": "0.75"
    },
    {
      "file": "e0b98aec-2122-4e44-b019-53dec1fccc2c.jpg",
      "width": 768,
      "height": 1024,
      "orientation": "portrait",
      "aspectRatio": "0.75"
    },
    {
      "file": "e0c3373d-278c-4ab5-b273-5d93c92913b8.jpg",
      "width": 768,
      "height": 1024,
      "orientation": "portrait",
      "aspectRatio": "0.75"
    },
    {
      "file": "e1028d37-60d1-410f-a994-611365c88f7e.jpg",
      "width": 768,
      "height": 1024,
      "orientation": "portrait",
      "aspectRatio": "0.75"
    },
    {
      "file": "e2628383-24c1-4168-88d9-14424e68e46b.jpg",
      "width": 768,
      "height": 1024,
      "orientation": "portrait",
      "aspectRatio": "0.75"
    },
    {
      "file": "e61428b7-f9b5-4ce1-84f5-d995f8bc9f5d.jpg",
      "width": 1200,
      "height": 1600,
      "orientation": "portrait",
      "aspectRatio": "0.75"
    },
    {
      "file": "ecbc698a-3993-4145-8bbb-95b3a76a29ab.jpg",
      "width": 1200,
      "height": 1600,
      "orientation": "portrait",
      "aspectRatio": "0.75"
    },
    {
      "file": "f0cf6d50-86a7-4ac4-9f2d-5fd7726da77a.jpg",
      "width": 785,
      "height": 1000,
      "orientation": "portrait",
      "aspectRatio": "0.79"
    },
    {
      "file": "f17a126d-cd5d-4e4f-bd54-e2cf424ee099.jpg",
      "width": 1280,
      "height": 1600,
      "orientation": "portrait",
      "aspectRatio": "0.80"
    },
    {
      "file": "f2659337-ad5b-4e3f-ae03-8745cd6f5f00.jpg",
      "width": 768,
      "height": 1024,
      "orientation": "portrait",
      "aspectRatio": "0.75"
    },
    {
      "file": "f30c8d8d-a78a-4000-80e4-0df766763455.jpg",
      "width": 768,
      "height": 1024,
      "orientation": "portrait",
      "aspectRatio": "0.75"
    },
    {
      "file": "f43ce639-d1a8-4ff5-9358-9b625c171817.jpg",
      "width": 768,
      "height": 1024,
      "orientation": "portrait",
      "aspectRatio": "0.75"
    },
    {
      "file": "f4957d98-18d3-4e4d-94d9-7ad01d436479.jpg",
      "width": 1200,
      "height": 1600,
      "orientation": "portrait",
      "aspectRatio": "0.75"
    },
    {
      "file": "f5c39e96-2755-4b3d-8123-10b0e8b7fd1e.jpg",
      "width": 768,
      "height": 1024,
      "orientation": "portrait",
      "aspectRatio": "0.75"
    },
    {
      "file": "f6eb8127-22f8-4c8c-b921-6e395f9c3579.jpg",
      "width": 768,
      "height": 1024,
      "orientation": "portrait",
      "aspectRatio": "0.75"
    },
    {
      "file": "f81c422c-31a7-42bb-b5cb-eadbd5b4a517.jpg",
      "width": 1200,
      "height": 1600,
      "orientation": "portrait",
      "aspectRatio": "0.75"
    },
    {
      "file": "f9a67171-4e00-4d49-bb2c-05de52c207fc.jpg",
      "width": 768,
      "height": 1024,
      "orientation": "portrait",
      "aspectRatio": "0.75"
    },
    {
      "file": "fc7388d0-dec0-4295-8c73-f4132a64b71e.jpg",
      "width": 768,
      "height": 1024,
      "orientation": "portrait",
      "aspectRatio": "0.75"
    }
  ]
}